prompt_version_manager.py
prompt_version_manager-0.1.0.dist-info/METADATA
prompt_version_manager-0.1.0.dist-info/WHEEL
prompt_version_manager-0.1.0.dist-info/top_level.txt
prompt_version_manager-0.1.0.dist-info/RECORD
