Metadata-Version: 2.4
Name: prompt_version_manager
Version: 0.1.0
Summary: A package to track and save prompt versions automatically
Home-page: https://github.com/parthrangarajan/prompt_version_manager
Author: Parth Rangarajan
Author-email: rangarajanparth@gmail.com
Classifier: Programming Language :: Python :: 3
Classifier: License :: OSI Approved :: MIT License
Classifier: Operating System :: OS Independent
Requires-Python: >=3.6
Dynamic: author
Dynamic: author-email
Dynamic: classifier
Dynamic: home-page
Dynamic: requires-python
Dynamic: summary
